GG14054UNO/__init__.py
GG14054UNO/linear_systems.py
GG14054UNO/nonlinear_systems.py
GG14054UNO/utils.py
gg14054uno-0.1.0.dist-info/licenses/LICENSE
gg14054uno-0.1.0.dist-info/METADATA
gg14054uno-0.1.0.dist-info/WHEEL
gg14054uno-0.1.0.dist-info/top_level.txt
gg14054uno-0.1.0.dist-info/RECORD
