Metadata-Version: 2.4
Name: GG14054UNO
Version: 0.1.0
Summary: Librería para resolver sistemas de ecuaciones lineales y no lineales. Corto CAD135
Home-page: https://github.com/LexterDev/GG14054UNO
Author: Walter Galicia
Author-email: Walter Galicia <gg14054@ues.edu.sv>
License: MIT
Requires-Python: >=3.6
License-File: LICENSE
Requires-Dist: numpy
Dynamic: author
Dynamic: home-page
Dynamic: license-file
Dynamic: requires-python
